{
  "version": 1,
  "license": "CC-BY-SA-3.0",
  "copyright": "Originally made by EmoGarbage, Modified by ItsAbby for Far Horizons, further modifed by Killer Tamashi for LENGTH and maximum michaelwaves",
  "size": {
    "x": 32,
    "y": 32
  },
  "states": [
    {
      "name": "icon"
    },
    {
      "name": "icon_0"
    },
    {
      "name": "icon_1"
    },
    {
      "name": "icon_2"
    },
    {
      "name": "icon_3"
    },
    {
      "name": "icon_4"
    },
    {
      "name": "icon_5"
    },
    {
      "name": "icon_6"
    },
    {
      "name": "icon_7"
    },
    {
      "name": "icon_8"
    },
    {
      "name": "icon_9"
    },
    {
      "name": "icon_10"
    },
    {
      "name": "icon_11"
    },
    {
      "name": "icon_12"
    },
    {
      "name": "icon_13"
    },
    {
      "name": "icon_14"
    },
    {
      "name": "icon_15"
    },
    {
      "name": "panel"
    },
    {
      "name": "unlit"
    },
    {
      "name": "inserting",
      "delays": [
        [
          0.1,
          0.1,
          0.1,
          0.1,
          0.1,
          0.1,
          0.1,
          0.1
        ]
      ]
    }
  ]
}
